{
  "transferencias": [
    {
      "id": 1,
      "valor": 35,
      "destino": "1212-1",
      "data": "2020-11-06T21:34:17.155Z"
    },
    {
      "id": 2,
      "valor": 40,
      "destino": "1213-1",
      "data": "2020-11-04T21:24:10.710Z"
    },
    {
      "valor": 20,
      "destino": "12421",
      "data": "2022-12-07T13:08:05.821Z",
      "id": 3
    },
    {
      "valor": 12445,
      "destino": "12314",
      "data": "2022-12-07T13:08:51.284Z",
      "id": 4
    },
    {
      "valor": 2412,
      "destino": "214124",
      "data": "2022-12-07T13:24:57.784Z",
      "id": 5
    },
    {
      "valor": 414,
      "destino": "424241",
      "data": "2022-12-07T13:27:11.560Z",
      "id": 6
    }
  ]
}